scaleway_core/__init__.py
scaleway_core/api.py
scaleway_core/bridge/__init__.py
scaleway_core/bridge/decimal.py
scaleway_core/bridge/money.py
scaleway_core/bridge/region.py
scaleway_core/bridge/scwfile.py
scaleway_core/bridge/serviceinfo.py
scaleway_core/bridge/timeseries.py
scaleway_core/bridge/zone.py
scaleway_core/client.py
scaleway_core/profile/__init__.py
scaleway_core/profile/env.py
scaleway_core/profile/file.py
scaleway_core/profile/profile.py
scaleway_core/py.typed
scaleway_core/utils/__init__.py
scaleway_core/utils/fetch_all_pages.py
scaleway_core/utils/project_or_organization_id.py
scaleway_core/utils/random_name.py
scaleway_core/utils/resolve_one_of.py
scaleway_core/utils/strenummeta.py
scaleway_core/utils/validate_path_param.py
scaleway_core/utils/waiter.py
scaleway_core/validations/__init__.py
scaleway_core/validations/string_validation.py
scaleway_core-2.10.2.dist-info/METADATA
scaleway_core-2.10.2.dist-info/WHEEL
scaleway_core-2.10.2.dist-info/RECORD
